swimlane-stubs/__init__.pyi
swimlane-stubs/core/__init__.pyi
swimlane-stubs/core/adapters/__init__.pyi
swimlane-stubs/core/adapters/app.pyi
swimlane-stubs/core/adapters/app_revision.pyi
swimlane-stubs/core/adapters/helper.pyi
swimlane-stubs/core/adapters/record.pyi
swimlane-stubs/core/adapters/record_revision.pyi
swimlane-stubs/core/adapters/report.pyi
swimlane-stubs/core/adapters/task.pyi
swimlane-stubs/core/adapters/usergroup.pyi
swimlane-stubs/core/bulk.pyi
swimlane-stubs/core/cache.pyi
swimlane-stubs/core/client.pyi
swimlane-stubs/core/cursor.pyi
swimlane-stubs/core/fields/__init__.pyi
swimlane-stubs/core/fields/attachment.pyi
swimlane-stubs/core/fields/base/__init__.pyi
swimlane-stubs/core/fields/base/cursor.pyi
swimlane-stubs/core/fields/base/field.pyi
swimlane-stubs/core/fields/base/multiselect.pyi
swimlane-stubs/core/fields/comment.pyi
swimlane-stubs/core/fields/datetime.pyi
swimlane-stubs/core/fields/history.pyi
swimlane-stubs/core/fields/list.pyi
swimlane-stubs/core/fields/number.pyi
swimlane-stubs/core/fields/reference.pyi
swimlane-stubs/core/fields/text.pyi
swimlane-stubs/core/fields/tracking.pyi
swimlane-stubs/core/fields/usergroup.pyi
swimlane-stubs/core/fields/valueslist.pyi
swimlane-stubs/core/resolver.pyi
swimlane-stubs/core/resources/__init__.pyi
swimlane-stubs/core/resources/app.pyi
swimlane-stubs/core/resources/app_revision.pyi
swimlane-stubs/core/resources/attachment.pyi
swimlane-stubs/core/resources/base.pyi
swimlane-stubs/core/resources/comment.pyi
swimlane-stubs/core/resources/record.pyi
swimlane-stubs/core/resources/record_revision.pyi
swimlane-stubs/core/resources/report.pyi
swimlane-stubs/core/resources/revision_base.pyi
swimlane-stubs/core/resources/task.pyi
swimlane-stubs/core/resources/usergroup.pyi
swimlane-stubs/core/search.pyi
swimlane-stubs/core/wrappedsession.pyi
swimlane-stubs/exceptions.pyi
swimlane-stubs/utils/__init__.pyi
swimlane-stubs/utils/version.pyi
swimlane_stubs-0.3.1.dist-info/WHEEL
swimlane_stubs-0.3.1.dist-info/METADATA
swimlane_stubs-0.3.1.dist-info/RECORD
