Metadata-Version: 2.1
Name: swimlane-stubs
Version: 0.3.1
Summary: A small library to help with type hinting for the Swimlane Python SDK
Author: Alex Way
Author-email: alexwa@softcat.com
Requires-Python: >=3.7,<4.0
Classifier: Programming Language :: Python :: 3
Classifier: Programming Language :: Python :: 3.7
Classifier: Programming Language :: Python :: 3.8
Classifier: Programming Language :: Python :: 3.9
Classifier: Programming Language :: Python :: 3.10
Classifier: Programming Language :: Python :: 3.11
